sbx/__init__.py
sbx/py.typed
sbx/version.txt
sbx/common/__init__.py
sbx/common/distributions.py
sbx/common/jax_layers.py
sbx/common/off_policy_algorithm.py
sbx/common/on_policy_algorithm.py
sbx/common/policies.py
sbx/common/type_aliases.py
sbx/common/utils.py
sbx/crossq/__init__.py
sbx/crossq/crossq.py
sbx/crossq/policies.py
sbx/ddpg/__init__.py
sbx/ddpg/ddpg.py
sbx/dqn/__init__.py
sbx/dqn/dqn.py
sbx/dqn/policies.py
sbx/ppo/__init__.py
sbx/ppo/policies.py
sbx/ppo/ppo.py
sbx/sac/__init__.py
sbx/sac/policies.py
sbx/sac/sac.py
sbx/td3/__init__.py
sbx/td3/policies.py
sbx/td3/td3.py
sbx/tqc/__init__.py
sbx/tqc/policies.py
sbx/tqc/tqc.py
sbx_rl-0.25.0.dist-info/licenses/LICENSE
sbx_rl-0.25.0.dist-info/licenses/NOTICE
sbx_rl-0.25.0.dist-info/METADATA
sbx_rl-0.25.0.dist-info/WHEEL
sbx_rl-0.25.0.dist-info/top_level.txt
sbx_rl-0.25.0.dist-info/RECORD
