Metadata-Version: 2.4
Name: sbx-rl
Version: 0.25.0
Summary: Jax version of Stable Baselines, implementations of reinforcement learning algorithms.
Home-page: https://github.com/araffin/sbx
Author: Antonin Raffin
Author-email: antonin.raffin@dlr.de
License: MIT
Keywords: reinforcement-learning-algorithms reinforcement-learning machine-learning gym gymnasium jax openai stable baselines toolbox python data-science
Classifier: Programming Language :: Python :: 3
Classifier: Programming Language :: Python :: 3.10
Classifier: Programming Language :: Python :: 3.11
Classifier: Programming Language :: Python :: 3.12
Classifier: Programming Language :: Python :: 3.13
Requires-Python: >=3.10
License-File: LICENSE
License-File: NOTICE
Requires-Dist: stable_baselines3<3.0,>=2.8.0a0
Requires-Dist: jax<0.9.0,>=0.4.24
Requires-Dist: jaxlib
Requires-Dist: flax
Requires-Dist: optax
Requires-Dist: tqdm
Requires-Dist: rich
Requires-Dist: tfp-nightly>=0.26.0.dev20250831
Provides-Extra: tests
Requires-Dist: pytest; extra == "tests"
Requires-Dist: pytest-cov; extra == "tests"
Requires-Dist: pytest-env; extra == "tests"
Requires-Dist: pytest-xdist; extra == "tests"
Requires-Dist: mypy; extra == "tests"
Requires-Dist: ruff>=0.3.1; extra == "tests"
Requires-Dist: black<26,>=25.1.0; extra == "tests"
Dynamic: author
Dynamic: author-email
Dynamic: classifier
Dynamic: description
Dynamic: description-content-type
Dynamic: home-page
Dynamic: keywords
Dynamic: license
Dynamic: license-file
Dynamic: provides-extra
Dynamic: requires-dist
Dynamic: requires-python
Dynamic: summary
